pyprog/ProgressBar.py
pyprog/ProgressIndicatorFraction.py
pyprog/__init__.py
pyprog-1.1.0.post2.dist-info/LICENSE
pyprog-1.1.0.post2.dist-info/METADATA
pyprog-1.1.0.post2.dist-info/WHEEL
pyprog-1.1.0.post2.dist-info/top_level.txt
pyprog-1.1.0.post2.dist-info/RECORD
