Metadata-Version: 2.1
Name: pyprog
Version: 1.1.0.post2
Summary: A library for creating super customizable progress indicators.
Home-page: https://github.com/Bill13579/pyprog
Author: BillK
Author-email: bluesky42624@gmail.com
License: GNU AGPLv3
Keywords: progress bar indicator pyprog
Platform: UNKNOWN
